WigglyRivers/AppFiles.py
WigglyRivers/VersionControl.py
WigglyRivers/__init__.py
WigglyRivers/nhd_extract/__init__.py
WigglyRivers/nhd_extract/nhd_extract.py
WigglyRivers/rivers/CompareMeanders.py
WigglyRivers/rivers/ReachExtraction.py
WigglyRivers/rivers/RiverFunctions.py
WigglyRivers/rivers/RiversNetwork.py
WigglyRivers/rivers/__init__.py
WigglyRivers/tests/__init__.py
WigglyRivers/tests/test_RiverNetwork.py
WigglyRivers/utilities/Logger.py
WigglyRivers/utilities/__init__.py
WigglyRivers/utilities/classExceptions.py
WigglyRivers/utilities/filesManagement.py
WigglyRivers/utilities/general_functions.py
WigglyRivers/utilities/graphs.py
WigglyRivers/utilities/interactivePlotly.py
WigglyRivers/utilities/utilities.py
WigglyRivers/wavelet_tree/TreeScale.py
WigglyRivers/wavelet_tree/WaveletTreeFunctions.py
WigglyRivers/wavelet_tree/__init__.py
WigglyRivers/wavelet_tree/waveletFunctions.py
wigglyrivers-1.1.1.dist-info/licenses/LICENSE
wigglyrivers-1.1.1.dist-info/METADATA
wigglyrivers-1.1.1.dist-info/WHEEL
wigglyrivers-1.1.1.dist-info/top_level.txt
wigglyrivers-1.1.1.dist-info/RECORD
