Metadata-Version: 2.4
Name: WigglyRivers
Version: 1.1.1
Summary: Exploring the multiscale meandering characteristics of river transects
Author-email: Daniel Gonzalez-Duque <gonzalez-duque.1@osu.edu>, Jesus Gomez-Velez <gomezvelezjd@ornl.gov>
Maintainer-email: Daniel Gonzalez-Duque <danielgondu@gmail.com>
License:                     GNU AFFERO GENERAL PUBLIC LICENSE
Project-URL: Homepage, https://github.com/gomezvelezlab/WigglyRivers
Project-URL: Documentation, https://gomezvelezlab.github.io/WigglyRivers
Project-URL: Repository, https://github.com/gomezvelezlab/WigglyRivers
Keywords: rivers,meandering,geomorphology,cwt,wavelet
Requires-Python: >=3.10
License-File: LICENSE
Requires-Dist: geopandas
Requires-Dist: h5py
Requires-Dist: simpledbf
Requires-Dist: statsmodels
Requires-Dist: seaborn
Requires-Dist: pyarrow
Requires-Dist: plotly
Requires-Dist: salem
Requires-Dist: anytree
Requires-Dist: circle-fit
Requires-Dist: python-dotenv
Requires-Dist: tqdm
Provides-Extra: dev
Requires-Dist: black; extra == "dev"
Requires-Dist: pytest; extra == "dev"
Dynamic: license-file
